tui_utilities/__init__.py
tui_utilities/console.py
tui_utilities/format.py
tui_utilities/structure.py
tui_utilities/validation.py
tui_utilities/_tlds/tlds.txt
tui_utilities-1.0.9.dist-info/METADATA
tui_utilities-1.0.9.dist-info/WHEEL
tui_utilities-1.0.9.dist-info/top_level.txt
tui_utilities-1.0.9.dist-info/RECORD
