Metadata-Version: 2.4
Name: tui_utilities
Version: 1.0.9
Summary: Personal-use console utilities library
Author-email: Guido Iván Gross <grossguidoivan@gmail.com>
License: MIT
Classifier: Programming Language :: Python :: 3
Classifier: Operating System :: OS Independent
Classifier: Intended Audience :: Developers
Classifier: Topic :: Software Development :: Libraries
Requires-Python: >=3.8
Requires-Dist: rich
Requires-Dist: readchar
Requires-Dist: requests
